{
"updated": "2026-07-19T05:10:20Z",
"days": [
{
"date": "2026-07-14",
"temp_max": 26.3,
"temp_min": 24.6,
"uv_max": 6.05,
"wind_max": 25.3,
"code": 80
},
{
"date": "2026-07-15",
"temp_max": 25.3,
"temp_min": 23.0,
"uv_max": 7.8,
"wind_max": 26.3,
"code": 80
},
{
"date": "2026-07-16",
"temp_max": 24.9,
"temp_min": 22.8,
"uv_max": 7.7,
"wind_max": 16.8,
"code": 80
},
{
"date": "2026-07-17",
"temp_max": 25.3,
"temp_min": 22.7,
"uv_max": 7.45,
"wind_max": 14.9,
"code": 80
},
{
"date": "2026-07-18",
"temp_max": 25.7,
"temp_min": 23.4,
"uv_max": 7.45,
"wind_max": 13.2,
"code": 80
},
{
"date": "2026-07-19",
"temp_max": 24.4,
"temp_min": 22.9,
"uv_max": 6.75,
"wind_max": 12.3,
"code": 95
},
{
"date": "2026-07-20",
"temp_max": 25.9,
"temp_min": 22.6,
"uv_max": 7.7,
"wind_max": 20.1,
"code": 2
},
{
"date": "2026-07-21",
"temp_max": 26.0,
"temp_min": 22.7,
"uv_max": 7.75,
"wind_max": 14.8,
"code": 3
},
{
"date": "2026-07-22",
"temp_max": 25.3,
"temp_min": 23.9,
"uv_max": 7.3,
"wind_max": 12.3,
"code": 80
},
{
"date": "2026-07-23",
"temp_max": 25.2,
"temp_min": 22.7,
"uv_max": 7.75,
"wind_max": 17.2,
"code": 80
}
],
"current": {
"temp": 23.0,
"feels_like": 26.4,
"humidity": 89,
"wind": 7.2,
"wind_dir": 174,
"uv": 1.35,
"code": 80
},
"hourly": [
{
"time": "2026-07-18T05:00",
"temp": 23.8,
"code": 3
},
{
"time": "2026-07-18T06:00",
"temp": 24.5,
"code": 3
},
{
"time": "2026-07-18T07:00",
"temp": 24.7,
"code": 3
},
{
"time": "2026-07-18T08:00",
"temp": 24.9,
"code": 2
},
{
"time": "2026-07-18T09:00",
"temp": 25.3,
"code": 2
},
{
"time": "2026-07-18T10:00",
"temp": 25.5,
"code": 2
},
{
"time": "2026-07-18T11:00",
"temp": 25.6,
"code": 2
},
{
"time": "2026-07-18T12:00",
"temp": 25.7,
"code": 3
},
{
"time": "2026-07-18T13:00",
"temp": 25.6,
"code": 3
},
{
"time": "2026-07-18T14:00",
"temp": 25.6,
"code": 3
},
{
"time": "2026-07-18T15:00",
"temp": 25.4,
"code": 3
},
{
"time": "2026-07-18T16:00",
"temp": 25.2,
"code": 3
},
{
"time": "2026-07-18T17:00",
"temp": 24.8,
"code": 3
},
{
"time": "2026-07-18T18:00",
"temp": 24.5,
"code": 3
},
{
"time": "2026-07-18T19:00",
"temp": 24.5,
"code": 3
},
{
"time": "2026-07-18T20:00",
"temp": 24.4,
"code": 3
},
{
"time": "2026-07-18T21:00",
"temp": 24.4,
"code": 3
},
{
"time": "2026-07-18T22:00",
"temp": 23.9,
"code": 80
},
{
"time": "2026-07-18T23:00",
"temp": 24.0,
"code": 3
},
{
"time": "2026-07-19T00:00",
"temp": 24.0,
"code": 80
},
{
"time": "2026-07-19T01:00",
"temp": 23.9,
"code": 3
},
{
"time": "2026-07-19T02:00",
"temp": 23.3,
"code": 80
},
{
"time": "2026-07-19T03:00",
"temp": 22.9,
"code": 80
},
{
"time": "2026-07-19T04:00",
"temp": 22.9,
"code": 95
},
{
"time": "2026-07-19T05:10",
"temp": 23.0,
"code": 80
}
]
}